[
  {
    "position": "AI Automation Engineer",
    "date": "16/03/2026",
    "status": "applied",
    "link": "https://de.indeed.com/viewjob?jk=125f56c8b0987854",
    "company": "Novada Labs GmbH",
    "category": "company"
  },
  {
    "position": "AI Automation Intern (M&A Integration Ops) (Summer 2026)",
    "date": "24/03/2026",
    "status": "applied",
    "link": "https://www.linkedin.com/jobs/view/4361041392/?trk=eml-email_job_alert_digest_01-primary_job_list-0-job_posting_3_jobid_4361041392_ssid_7249756122_fmid_bamsw8~mn3flyv7~5z&refId=PS917RVohIIXwVBYbhTtxQ%3D%3D&trackingId=9wP8rdZPd6SzUw3O7se%2FsQ%3D%3D",
    "company": "Cloudflare",
    "category": "company"
  },
  {
    "position": "AI Solutions Engineer (Entry-Level)",
    "date": "25/03/2026",
    "status": "applied",
    "link": "https://www.linkedin.com/jobs/view/4380454400/?eBP=NOT_ELIGIBLE_FOR_CHARGING",
    "company": "Proxima Fusion",
    "category": "company"
  },
  {
    "position": "AI, Business Analyst, Information Technology - New York",
    "date": "23/03/2026",
    "status": "applied",
    "link": "https://www.linkedin.com/jobs/view/4362982748/?trk=eml-email_job_alert_digest_01-primary_job_list-0-job_posting_1_jobid_4362982748_ssid_4984020545_fmid_bamsw8~mn371bke~hl&refId=10keMsFWcy8hvuw1R2jMSQ%3D%3D&trackingId=bxFP63s9CjDC%2Fia6DzQb8Q%3D%3D",
    "company": "Moelis & Company",
    "category": "company"
  },
  {
    "position": "Agent Dev Engineer (FullTime&Intern)",
    "date": "17/03/2026",
    "status": "applied",
    "link": "https://www.linkedin.com/jobs/view/4383715891/",
    "company": "Flowith",
    "category": "company"
  },
  {
    "position": "Agent Engineer (New Grad, Summer 2026)",
    "date": "25/03/2026",
    "status": "applied",
    "link": "https://www.linkedin.com/jobs/search/?currentJobId=4332086664&f_C=96144957&originToLandingJobPostings=4332086664%2C4318238126%2C4340368307%2C4371060326&trk=d_flagship3_company_posts",
    "company": "Assort Health",
    "category": "company"
  },
  {
    "position": "Analytics Intern",
    "date": "23/03/2026",
    "status": "applied",
    "link": "https://www.linkedin.com/jobs/search-results/?currentJobId=4381473015&keywords=Data&origin=JOB_SEARCH_PAGE_JOB_FILTER&referralSearchId=hl3Qutsj2yd4Id86ZBdYTA%3D%3D&geoId=101282230&f_SAL=f_SA_id_227001%3A276001",
    "company": "Brunch",
    "category": "company"
  },
  {
    "position": "Data Analyst (AI Track)",
    "date": "26/03/2026",
    "status": "applied",
    "link": "https://wellfound.com/jobs/applications/979780241-3900615",
    "company": "MEDvidi",
    "category": "startup"
  },
  {
    "position": "Data Analyst",
    "date": "26/03/2026",
    "status": "applied",
    "link": "https://wellfound.com/jobs/applications/979779515-3962576",
    "company": "TECHSPO Toronto",
    "category": "startup"
  },
  {
    "position": "Early Career People Projects",
    "date": "24/03/2026",
    "status": "applied",
    "link": "https://www.linkedin.com/jobs/view/4342135414/?trk=eml-email_job_alert_digest_01-primary_job_list-0-job_posting_2_jobid_4342135414_ssid_7249756122_fmid_bamsw8~mn3flyv7~5z&refId=PS917RVohIIXwVBYbhTtxQ%3D%3D&trackingId=RNFMt2ctu72Hq00%2FEkoHxQ%3D%3D",
    "company": "Notion",
    "category": "company"
  },
  {
    "position": "Entry Level AI-First Transformation – Strategy Consultant",
    "date": "30/03/2026",
    "status": "applied",
    "link": "https://www.linkedin.com/jobs/view/4390542309/?trk=eml-email_job_alert_digest_01-primary_job_list-0-job_posting_1_jobid_4390542309_ssid_7249756122_fmid_bamsw8~mnakta02~n3&refId=xW9NZwPxZWrbntGv9nM30Q%3D%3D&trackingId=wbxHVaxZoNIUSmha0DOvjw%3D%3D",
    "company": "IBM",
    "category": "company"
  },
  {
    "position": "Intern - Data & AI Innovation at Allianz SE",
    "date": "11/03/2026",
    "status": "applied",
    "link": "https://careers.allianz.com/global/en/job/93235/Intern---Data--AI-Innovation-at-Allianz-SE-m-f-d",
    "company": "Allianz_SE",
    "category": "company"
  },
  {
    "position": "Intern AI Engineer - Customer Journey Analytics & Data Science",
    "date": "12/03/2026",
    "status": "reject",
    "link": "https://www.bmwgroup.jobs/de/de/jobfinder/job-description.158729.html?tl=coo%3Alinkedin",
    "company": "BMW",
    "category": "company"
  },
  {
    "position": "Intern Artificial Intelligence",
    "date": "12/03/2026",
    "status": "reject",
    "link": "https://careers.munichre.com/en/job/munich/intern-artificial-intelligence-m-f-d/3342/35537000064",
    "company": "Munich RE",
    "category": "company"
  },
  {
    "position": "Intern Data Analytics (all genders)",
    "date": "11/03/2026",
    "status": "reject",
    "link": "https://www.holidu.com/careers/intern-data-analytics-all-genders?src=Linkedin",
    "company": "Holidu",
    "category": "company"
  },
  {
    "position": "Intern, Global External Operations Digital Strategy - AI",
    "date": "30/03/2026",
    "status": "applied",
    "link": "https://www.linkedin.com/jobs/view/4390871402/?trk=eml-email_job_alert_digest_01-primary_job_list-0-job_posting_5_jobid_4390871402_ssid_7249756122_fmid_bamsw8~mnakta02~n3&refId=xW9NZwPxZWrbntGv9nM30Q%3D%3D&trackingId=mSd8P5KBG6LViaeSB4aUnA%3D%3D",
    "company": "BioSpace",
    "category": "company"
  },
  {
    "position": "Internship - Machine Learning Research Engineer",
    "date": "17/03/2026",
    "status": "applied",
    "link": "https://jobs.ashbyhq.com/Perplexity/b9e1ff15-d52a-46d5-abf0-26460f2a116c",
    "company": "Perplexity",
    "category": "company"
  },
  {
    "position": "Junior Analytics Engineer",
    "date": "16/03/2026",
    "status": "reject",
    "link": "https://n26.com/en-eu/careers/positions/7709763?gh_jid=7709763&gh_src=71b7b4e01",
    "company": "N26",
    "category": "company"
  },
  {
    "position": "Machine Learning Intern",
    "date": "26/03/2026",
    "status": "applied",
    "link": "https://wellfound.com/jobs?job_listing_slug=4015386-machine-learning-intern",
    "company": "Dataqueue",
    "category": "startup"
  },
  {
    "position": "Test Position",
    "date": "",
    "status": "applied",
    "link": "",
    "company": "Test",
    "category": "company"
  }
]